lablink_client_service/__init__.py
lablink_client_service/check_gpu.py
lablink_client_service/connect_crd.py
lablink_client_service/database.py
lablink_client_service/logger_config.py
lablink_client_service/subscribe.py
lablink_client_service/update_inuse_status.py
lablink_client_service/conf/__init__.py
lablink_client_service/conf/structured_config.py
lablink_client_service-0.0.4.dist-info/METADATA
lablink_client_service-0.0.4.dist-info/WHEEL
lablink_client_service-0.0.4.dist-info/entry_points.txt
lablink_client_service-0.0.4.dist-info/top_level.txt
lablink_client_service-0.0.4.dist-info/RECORD
