Metadata-Version: 2.4
Name: lablink-client-service
Version: 0.0.4
Summary: Lablink Client Service that will be installed in the lablink-client-base-image
Author-email: Amitha Attapu <amithaattapu0509@gmail.com>, Andrew Park <hep003@ucsd.edu>
Project-URL: Homepage, https://github.com/talmolab/lablink
Project-URL: Issues, https://github.com/talmolab/lablink/issues
Keywords: vm,docker,postgres,tutorial
Requires-Dist: psycopg2-binary>=2.9
Requires-Dist: requests>=2.31.0
Requires-Dist: hydra-core>=1.3
Requires-Dist: omegaconf>=2.3
Requires-Dist: psutil
Provides-Extra: dev
Requires-Dist: toml; extra == "dev"
Requires-Dist: twine; extra == "dev"
Requires-Dist: build; extra == "dev"
Requires-Dist: pytest; extra == "dev"
Requires-Dist: black; extra == "dev"
Requires-Dist: python-dotenv; extra == "dev"
